Metadata-Version: 1.0
Name: gb78-distributions-7
Version: 1.0
Summary: Gaussian distributions
Home-page: UNKNOWN
Author: Daniel Pedraza
Author-email: dpedrazatrivino2@gmail.com
License: UNKNOWN
Platform: UNKNOWN
